ff_fasttext_api/__init__.py
ff_fasttext_api/healthcheck.py
ff_fasttext_api/logger.py
ff_fasttext_api/scripts/__init__.py
ff_fasttext_api/scripts/ff_fasttext.py
ff_fasttext_api/server.py
ff_fasttext_api-0.0.1.dist-info/entry_points.txt
ff_fasttext_api-0.0.1.dist-info/LICENSE
ff_fasttext_api-0.0.1.dist-info/WHEEL
ff_fasttext_api-0.0.1.dist-info/METADATA
ff_fasttext_api-0.0.1.dist-info/RECORD
